qtoggleserver/pylontech/__init__.py
qtoggleserver/pylontech/battery.py
qtoggleserver/pylontech/ports.py
qtoggleserver_pylontech-1.2.0.dist-info/licenses/LICENSE.txt
qtoggleserver_pylontech-1.2.0.dist-info/METADATA
qtoggleserver_pylontech-1.2.0.dist-info/WHEEL
qtoggleserver_pylontech-1.2.0.dist-info/top_level.txt
qtoggleserver_pylontech-1.2.0.dist-info/RECORD
