Metadata-Version: 2.4
Name: qtoggleserver-pylontech
Version: 1.2.0
Summary: Pylontech batteries support for qToggleServer
Author-email: Calin Crisan <ccrisan@gmail.com>
License: Apache 2.0
Requires-Python: >=3.11
License-File: LICENSE.txt
Requires-Dist: pyserial
Requires-Dist: python-pylontech
Dynamic: license-file
